LICENSE
MANIFEST.in
README.rst
setup.cfg
setup.py
versioneer.py
artellapipe/__init__.py
artellapipe/tools/__init__.py
artellapipe/tools/alembicmanager/__init__.py
artellapipe/tools/alembicmanager/__logging__.ini
artellapipe/tools/alembicmanager/__version__.py
artellapipe/tools/alembicmanager/_version.py
artellapipe/tools/alembicmanager/core/__init__.py
artellapipe/tools/alembicmanager/core/alembicmanager.py
artellapipe/tools/alembicmanager/resources/images/alembicmanager_logo.png
artellapipe/tools/alembicmanager/widgets/__init__.py
artellapipe/tools/alembicmanager/widgets/alembicmanager.py
artellapipe/tools/alembicmanager/widgets/base/__init__.py
artellapipe/tools/alembicmanager/widgets/base/alembicexporter.py
artellapipe/tools/alembicmanager/widgets/base/alembicimporter.py
artellapipe/tools/alembicmanager/widgets/houdini/__init__.py
artellapipe/tools/alembicmanager/widgets/houdini/alembicimporter.py
artellapipe/tools/alembicmanager/widgets/maya/__init__.py
artellapipe/tools/alembicmanager/widgets/maya/alembiceimporter.py
artellapipe_tools_alembicmanager.egg-info/PKG-INFO
artellapipe_tools_alembicmanager.egg-info/SOURCES.txt
artellapipe_tools_alembicmanager.egg-info/dependency_links.txt
artellapipe_tools_alembicmanager.egg-info/not-zip-safe
artellapipe_tools_alembicmanager.egg-info/requires.txt
artellapipe_tools_alembicmanager.egg-info/top_level.txt
tests/__init__.py
tests/test_general.py