Metadata-Version: 2.1
Name: artellapipe-tools-alembicmanager
Version: 0.0.6
Summary: Tool to import/export Alembic files
Home-page: https://github.com/ArtellaPipe/artellapipe-tools-alembicmanager
Author: Tomas Poveda
Author-email: tpovedatd@gmail.com
License: MIT
Platform: UNKNOWN
Provides-Extra: dev
Provides-Extra: test
